spey/__init__.py
spey/_version.py
spey/about.py
spey/helper_functions.py
spey/math.py
spey/utils.py
spey/backends/__init__.py
spey/backends/distributions.py
spey/backends/default_pdf/__init__.py
spey/backends/default_pdf/simple_pdf.py
spey/backends/default_pdf/third_moment.py
spey/backends/default_pdf/uncertainty_synthesizer.py
spey/base/__init__.py
spey/base/backend_base.py
spey/base/hypotest_base.py
spey/base/model_config.py
spey/combiner/__init__.py
spey/combiner/uncorrelated_statistics_combiner.py
spey/hypothesis_testing/__init__.py
spey/hypothesis_testing/asymptotic_calculator.py
spey/hypothesis_testing/distributions.py
spey/hypothesis_testing/test_statistics.py
spey/hypothesis_testing/toy_calculator.py
spey/hypothesis_testing/upper_limits.py
spey/hypothesis_testing/utils.py
spey/interface/__init__.py
spey/interface/statistical_model.py
spey/optimizer/__init__.py
spey/optimizer/core.py
spey/optimizer/minuit_tools.py
spey/optimizer/scipy_tools.py
spey/system/__init__.py
spey/system/exceptions.py
spey/system/logger.py
spey/system/webutils.py
spey-0.2.6.dist-info/licenses/LICENSE
spey-0.2.6.dist-info/METADATA
spey-0.2.6.dist-info/WHEEL
spey-0.2.6.dist-info/entry_points.txt
spey-0.2.6.dist-info/top_level.txt
spey-0.2.6.dist-info/RECORD
