Metadata-Version: 2.4
Name: spey
Version: 0.2.6
Summary: Smooth inference for reinterpretation studies
Home-page: https://github.com/SpeysideHEP/spey
Download-URL: https://github.com/SpeysideHEP/spey/archive/refs/tags/v0.2.6.tar.gz
Author: Jack Y. Araz
Author-email: j.araz@ucl.ac.uk
License: MIT
Project-URL: Bug Tracker, https://github.com/SpeysideHEP/spey/issues
Project-URL: Documentation, https://spey.readthedocs.io
Project-URL: Repository, https://github.com/SpeysideHEP/spey
Project-URL: Homepage, https://github.com/SpeysideHEP/spey
Project-URL: Download, https://github.com/SpeysideHEP/spey/archive/refs/tags/v0.2.6.tar.gz
Classifier: Intended Audience :: Science/Research
Classifier: License :: OSI Approved :: MIT License
Classifier: Operating System :: OS Independent
Classifier: Topic :: Scientific/Engineering :: Physics
Classifier: Programming Language :: Python
Classifier: Programming Language :: Python :: 3
Classifier: Programming Language :: Python :: 3.9
Classifier: Programming Language :: Python :: 3.10
Classifier: Programming Language :: Python :: 3.11
Classifier: Programming Language :: Python :: 3.12
Classifier: Programming Language :: Python :: 3.13
Requires-Python: >3.8, <3.14
License-File: LICENSE
Requires-Dist: numpy<3.0.0,>=1.21.6
Requires-Dist: scipy>=1.10.0
Requires-Dist: autograd>=1.7.0
Requires-Dist: semantic_version~=2.10
Requires-Dist: tqdm>=4.64.0
Requires-Dist: requests>=2.31.0
Requires-Dist: setuptools
Provides-Extra: dev
Requires-Dist: pytest>=7.1.2; extra == "dev"
Requires-Dist: pytest-cov>=3.0.0; extra == "dev"
Requires-Dist: twine>=3.7.1; extra == "dev"
Requires-Dist: wheel>=0.37.1; extra == "dev"
Provides-Extra: iminuit
Requires-Dist: iminuit>=2.22.0; extra == "iminuit"
Dynamic: author
Dynamic: author-email
Dynamic: classifier
Dynamic: description
Dynamic: description-content-type
Dynamic: download-url
Dynamic: home-page
Dynamic: license
Dynamic: license-file
Dynamic: project-url
Dynamic: provides-extra
Dynamic: requires-dist
Dynamic: requires-python
Dynamic: summary
